DIYables_MicroPython_LED/DIYables_MicroPython_LED.py
DIYables_MicroPython_LED/__init__.py
DIYables_MicroPython_LED-0.1.1.dist-info/LICENSE
DIYables_MicroPython_LED-0.1.1.dist-info/METADATA
DIYables_MicroPython_LED-0.1.1.dist-info/WHEEL
DIYables_MicroPython_LED-0.1.1.dist-info/top_level.txt
DIYables_MicroPython_LED-0.1.1.dist-info/RECORD
